polidoro_cli/__init__.py
polidoro_cli/main.py
polidoro_cli/cli/__init__.py
polidoro_cli/cli/cli.py
polidoro_cli/clis/__init__.py
polidoro_cli/clis/django.py
polidoro_cli/clis/django.yml
polidoro_cli/clis/docker.py
polidoro_cli/clis/docker.yml
polidoro_cli/clis/elixir.yml
polidoro_cli/clis/git.py
polidoro_cli/clis/git.yml
polidoro_cli/clis/github.yml
polidoro_cli/clis/github_cli.py
polidoro_cli/clis/gitlab.yml
polidoro_cli/clis/gitlab_cli.py
polidoro_cli/clis/kubectl.py
polidoro_cli/clis/kubectl.yml
polidoro_cli/clis/npm.yml
polidoro_cli/clis/postgres.yml
polidoro_cli/clis/python.yml
polidoro_cli/clis/elixir/Dockerfile
polidoro_cli/clis/elixir/docker-compose.yml
polidoro_cli-4.6.8.data/scripts/cli
polidoro_cli-4.6.8.dist-info/LICENSE
polidoro_cli-4.6.8.dist-info/METADATA
polidoro_cli-4.6.8.dist-info/WHEEL
polidoro_cli-4.6.8.dist-info/top_level.txt
polidoro_cli-4.6.8.dist-info/RECORD
