Metadata-Version: 2.1
Name: polidoro-cli
Version: 4.6.8
Summary: Polidoro CLI.
Home-page: https://github.com/heitorpolidoro/polidoro-cli
Author: Heitor Polidoro
License: MIT
Platform: UNKNOWN
Classifier: Programming Language :: Python :: 3
Classifier: License :: OSI Approved :: MIT License
Classifier: Operating System :: OS Independent
License-File: LICENSE
Requires-Dist: polidoro-argument (>=4.0)
Requires-Dist: pyyaml
